odoo/addons/base_jsonify/README.rst
odoo/addons/base_jsonify/__init__.py
odoo/addons/base_jsonify/__manifest__.py
odoo/addons/base_jsonify/demo/export_demo.xml
odoo/addons/base_jsonify/demo/ir.exports.line.csv
odoo/addons/base_jsonify/demo/resolver_demo.xml
odoo/addons/base_jsonify/i18n/base_jsonify.pot
odoo/addons/base_jsonify/i18n/zh_CN.po
odoo/addons/base_jsonify/models/__init__.py
odoo/addons/base_jsonify/models/ir_exports.py
odoo/addons/base_jsonify/models/ir_exports_line.py
odoo/addons/base_jsonify/models/ir_exports_resolver.py
odoo/addons/base_jsonify/models/models.py
odoo/addons/base_jsonify/models/utils.py
odoo/addons/base_jsonify/readme/CONTRIBUTORS.rst
odoo/addons/base_jsonify/readme/DESCRIPTION.rst
odoo/addons/base_jsonify/security/ir.model.access.csv
odoo/addons/base_jsonify/static/description/icon.png
odoo/addons/base_jsonify/static/description/index.html
odoo/addons/base_jsonify/tests/__init__.py
odoo/addons/base_jsonify/tests/test_get_parser.py
odoo/addons/base_jsonify/tests/test_helpers.py
odoo/addons/base_jsonify/tests/test_ir_exports_line.py
odoo/addons/base_jsonify/views/ir_exports_resolver_view.xml
odoo/addons/base_jsonify/views/ir_exports_view.xml
odoo14_addon_base_jsonify-14.0.1.5.0.dist-info/METADATA
odoo14_addon_base_jsonify-14.0.1.5.0.dist-info/WHEEL
odoo14_addon_base_jsonify-14.0.1.5.0.dist-info/top_level.txt
odoo14_addon_base_jsonify-14.0.1.5.0.dist-info/RECORD
