Metadata-Version: 2.1
Name: odoo14-addon-base-jsonify
Version: 14.0.1.5.0
Summary: Base module that provide the jsonify method on all models
Home-page: https://github.com/OCA/server-tools
Author: Akretion, Odoo Community Association (OCA)
Author-email: support@odoo-community.org
License: LGPL-3
Platform: UNKNOWN
Classifier: Programming Language :: Python
Classifier: Framework :: Odoo
Classifier: Framework :: Odoo :: 14.0
Classifier: License :: OSI Approved :: GNU Lesser General Public License v3 (LGPLv3)
Requires-Python: >=3.6
Requires-Dist: odoo (<14.1dev,>=14.0a)
